django_authz_tools/__init__.py
django_authz_tools/apps.py
django_authz_tools/auth_backends.py
django_authz_tools/consts.py
django_authz_tools/exceptions.py
django_authz_tools/helpers/__init__.py
django_authz_tools/helpers/misc.py
django_authz_tools/helpers/model_utils.py
django_authz_tools/helpers/settings_utils.py
django_authz_tools/helpers/var_parser.py
django_authz_tools/models/__init__.py
django_authz_tools/models/base.py
django_authz_tools/models/impls/__init__.py
django_authz_tools/models/impls/ac_0d.py
django_authz_tools/models/impls/ac_1d.py
django_authz_tools/models/impls/ac_2d.py
django_authz_tools/models/impls/ac_3d.py
django_authz_tools/models/managers.py
django_authz_tools/models/mixins.py
django_authz_tools/settings.py
django_authz_tools/tests/__init__.py
django_authz_tools-0.1.1.dist-info/LICENSE
django_authz_tools-0.1.1.dist-info/METADATA
django_authz_tools-0.1.1.dist-info/WHEEL
django_authz_tools-0.1.1.dist-info/RECORD
