Metadata-Version: 2.1
Name: django-authz-tools
Version: 0.1.1
Summary: A collection of built shortcut models and helpers to ease the creation of authorization system in Django projects with not complicated flows
Home-page: https://github.com/rwrotson/django-authz-tools
License: MIT
Keywords: django,plugin,authorization,auth,authz,groups,permissions
Author: Igor Lashkov
Author-email: rwrotson@yandex.ru
Requires-Python: ==3.11.1
Classifier: License :: OSI Approved :: MIT License
Classifier: Programming Language :: Python :: 3
Requires-Dist: django (==4.2.3)
Project-URL: Repository, https://github.com/rwrotson/django-authz-tools
